geompct/classic_comb_opt.py
geompct/combinatorial.py
geompct/eval_metrics.py
geompct/ml_classif.py
geompct/pentagon.py
geompct/preprocess.py
geompct/sim_metric.py
geompct/utils.py
geompct-2.0.5.2.dist-info/METADATA
geompct-2.0.5.2.dist-info/WHEEL
geompct-2.0.5.2.dist-info/licenses/LICENSE
geompct-2.0.5.2.dist-info/RECORD
