Metadata-Version: 2.4
Name: geompct
Version: 2.0.5.2
Summary: Accurate Pentagon Copying Test (PCT) evaluation using Combinatorial Optimization and Geometric Theory
Project-URL: Homepage, https://github.com/htdgv/geompct
Project-URL: Bug Reports, https://github.com/htdgv/geompct/issues
Project-URL: Source, https://github.com/htdgv/geompct
Author-email: Duong Vu <duong.vht@vinuni.edu.vn>, Hieu Pham <hieu.ph@vinuni.edu.vn>
Maintainer-email: Duong Vu <duong.vht@vinuni.edu.vn>
License: MIT License
License-File: LICENSE
Keywords: clinical-decision-support,cognitive-assessment,combinatorial-optimization,computational-geometry,explainable-ai,neuropsychological-assessment,pentagon-copying-test
Classifier: Development Status :: 3 - Alpha
Classifier: Intended Audience :: Developers
Classifier: License :: OSI Approved :: MIT License
Classifier: Programming Language :: Python :: 3.10
Classifier: Programming Language :: Python :: 3.11
Classifier: Programming Language :: Python :: 3.12
Classifier: Topic :: Scientific/Engineering :: Image Processing
Classifier: Topic :: Scientific/Engineering :: Medical Science Apps.
Requires-Python: >=3.10
Requires-Dist: matplotlib
Requires-Dist: numpy
Requires-Dist: omegaconf
Requires-Dist: opencv-contrib-python
Requires-Dist: opencv-python
Requires-Dist: pandas
Requires-Dist: pyyaml
Requires-Dist: scikit-image
Requires-Dist: scikit-learn
Requires-Dist: scipy
Requires-Dist: seaborn
Requires-Dist: shapely
Requires-Dist: tqdm
Provides-Extra: dev
Requires-Dist: black; extra == 'dev'
Requires-Dist: flake8; extra == 'dev'
Requires-Dist: isort; extra == 'dev'
Requires-Dist: mypy; extra == 'dev'
Requires-Dist: pytest; extra == 'dev'
Requires-Dist: pytest-cov; extra == 'dev'
